fish_pen/__init__.py
fish_pen-0.0.4.dist-info/LICENSE
fish_pen-0.0.4.dist-info/METADATA
fish_pen-0.0.4.dist-info/WHEEL
fish_pen-0.0.4.dist-info/top_level.txt
fish_pen-0.0.4.dist-info/RECORD
