Metadata-Version: 2.1
Name: fish-pen
Version: 0.0.4
Summary: Package for demonstration purposes in documentation
Home-page: https://gitgud.io/fish/fish-pen
Author: Fisherman's Friend
Author-email: fish@waifu.club
License: UNKNOWN
Project-URL: Documentation, https://fish-pen.readthedocs.org
Project-URL: Source, https://gitgud.io/fish/fish-pen
Platform: UNKNOWN
Classifier: License :: OSI Approved :: GNU Lesser General Public License v3 or later (LGPLv3+)
Classifier: Programming Language :: Python :: 3
Classifier: Operating System :: OS Independent
